mongoit/__init__.py
mongoit/document/__init__.py
mongoit/document/document.py
mongoit/document/field_access.py
mongoit/document/query.py
mongoit/fields/__init__.py
mongoit/fields/array_field.py
mongoit/fields/boolean_field.py
mongoit/fields/const_field.py
mongoit/fields/datetime_field.py
mongoit/fields/field.py
mongoit/fields/number_fields.py
mongoit/fields/object_field.py
mongoit/fields/object_fields.py
mongoit/fields/string_field.py
mongomodels/__init__.py
mongomodels/document/__init__.py
mongomodels/document/document.py
mongomodels/document/field_access.py
mongomodels/document/query.py
mongomodels/fields/__init__.py
mongomodels/fields/array_field.py
mongomodels/fields/boolean_field.py
mongomodels/fields/const_field.py
mongomodels/fields/datetime_field.py
mongomodels/fields/field.py
mongomodels/fields/number_fields.py
mongomodels/fields/object_field.py
mongomodels/fields/object_fields.py
mongomodels/fields/string_field.py
mongoit-0.0.2.dist-info/METADATA
mongoit-0.0.2.dist-info/WHEEL
mongoit-0.0.2.dist-info/top_level.txt
mongoit-0.0.2.dist-info/RECORD
